pkg_template/__init__.py
pkg_template/cli.py
pkg_template/data/django_app/__init__.py
pkg_template/data/django_app/admin.py
pkg_template/data/django_app/apps.py
pkg_template/data/django_app/models.py
pkg_template/data/django_app/tests.py
pkg_template/data/django_app/urls.py
pkg_template/data/django_app/views.py
pkg_template/data/django_app/migrations/__init__.py
pkg_template-0.1.9.dist-info/LICENSE
pkg_template-0.1.9.dist-info/METADATA
pkg_template-0.1.9.dist-info/WHEEL
pkg_template-0.1.9.dist-info/entry_points.txt
pkg_template-0.1.9.dist-info/top_level.txt
pkg_template-0.1.9.dist-info/RECORD
