Metadata-Version: 2.1
Name: pkg-template
Version: 0.1.9
Summary: a template maker
Home-page: https://github.com/amirgard0/pkg-template
Author: amirgard
Author-email: 
Classifier: Programming Language :: Python :: 3
Classifier: License :: OSI Approved :: MIT License
Classifier: Operating System :: OS Independent
Requires-Python: >=3.6
License-File: LICENSE
Requires-Dist: django
